mem/__init__.py
mem/test.py
mem-1.0.1.dist-info/METADATA
mem-1.0.1.dist-info/WHEEL
mem-1.0.1.dist-info/top_level.txt
mem-1.0.1.dist-info/RECORD
